{"slider":[{"src":"images\/960kh640.jpg","type":"image","id":"5dd682969504d"},{"src":"videos\/333333.mp4","type":"video","id":"5dd682fe29b53"},{"src":"images\/5.jpg","type":"image","id":"5dd683ebbbb2e"},{"src":"images\/1.jpg","type":"image","id":"5dd683f0f0bf7"},{"src":"images\/4.jpg","type":"image","id":"5dd6840404fa1"},{"src":"images\/6.jpg","type":"image","id":"5dd6840b19b44"},{"src":"images\/7.jpg","type":"image","id":"5dd68412e11e2"},{"src":"images\/2.jpg","type":"image","id":"5dd6849a1bbee"},{"src":"images\/3.jpg","type":"image","id":"5dd684a00fe29"}]}